dzidulaflix/__init__.py
dzidulaflix/models.py
dzidulaflix/views.py
dzidula-1.0.0.dist-info/METADATA
dzidula-1.0.0.dist-info/WHEEL
dzidula-1.0.0.dist-info/top_level.txt
dzidula-1.0.0.dist-info/RECORD
