Metadata-Version: 2.1
Name: dzidula
Version: 1.0.0
Summary: winner
Home-page: UNKNOWN
License: UNKNOWN
Platform: UNKNOWN
